setup.py
yadage_service_cli.egg-info/PKG-INFO
yadage_service_cli.egg-info/SOURCES.txt
yadage_service_cli.egg-info/dependency_links.txt
yadage_service_cli.egg-info/entry_points.txt
yadage_service_cli.egg-info/requires.txt
yadage_service_cli.egg-info/top_level.txt
yadagesvccli/__init__.py
yadagesvccli/cli.py
yadagesvccli/client.py