Metadata-Version: 1.0
Name: yadage-service-cli
Version: 0.1.10
Summary: yadage service command line tools
Home-page: http://github.com/yadage/yadage-service-cli
Author: Kyle Cranmer, Lukas Heinrich
Author-email: cranmer@cern.ch, lukas.heinrich@cern.ch
License: UNKNOWN
Platform: UNKNOWN
